{"stats":{"minecraft:custom":{"minecraft:interact_with_furnace":28,"minecraft:mob_kills":20,"minecraft:knockouts":4,"minecraft:interact_with_crafting_table":15,"minecraft:leave_game":6,"minecraft:time_since_death":21644,"minecraft:time_since_rest":21731,"minecraft:sprint_one_cm":134194,"minecraft:damage_absorbed":107,"minecraft:damage_taken":1491,"minecraft:walk_one_cm":90856,"minecraft:drop":16,"minecraft:damage_dealt":2392,"minecraft:swim_one_cm":7057,"minecraft:fly_one_cm":517778,"minecraft:open_chest":2,"minecraft:crouch_one_cm":8252,"minecraft:play_time":66001,"minecraft:deaths":2,"minecraft:sneak_time":3469,"minecraft:walk_under_water_one_cm":422,"minecraft:jump":1322,"minecraft:walk_on_water_one_cm":1021,"minecraft:total_world_time":66001,"minecraft:fall_one_cm":53150},"minecraft:crafted":{"minecraft:cooked_beef":11,"minecraft:wooden_sword":1,"regions_unexplored:maple_branch":2,"minecraft:wooden_shovel":1,"minecraft:stone_shovel":1,"minecraft:cooked_porkchop":7,"minecraft:crafting_table":4,"regions_unexplored:maple_planks":32,"minecraft:wooden_pickaxe":1,"minecraft:furnace":1,"minecraft:birch_planks":148,"minecraft:stone_axe":1,"minecraft:cooked_mutton":4,"minecraft:air":0,"minecraft:stick":20,"minecraft:stone_pickaxe":1,"minecraft:wooden_axe":1,"minecraft:stone_sword":1,"minecraft:birch_sign":6},"minecraft:mined":{"regions_unexplored:orange_coneflower":2,"regions_unexplored:maple_planks":5,"regions_unexplored:maple_log":9,"minecraft:crafting_table":1,"minecraft:short_grass":6,"minecraft:grass_block":1,"regions_unexplored:silt_dirt":10,"minecraft:chest":2,"regions_unexplored:silver_birch_shrub":1,"regions_unexplored:aster":1,"regions_unexplored:maple_leaves":1,"minecraft:sugar_cane":1,"minecraft:wall_torch":1,"regions_unexplored:tsubaki":2,"minecraft:light_weighted_pressure_plate":2,"minecraft:birch_planks":2,"regions_unexplored:stone_bud":2,"minecraft:furnace":2,"minecraft:fire":33,"regions_unexplored:orange_maple_leaves":2,"minecraft:moss_carpet":3,"minecraft:pumpkin":10,"minecraft:coal_ore":15,"regions_unexplored:red_maple_leaves":2,"regions_unexplored:silver_birch_log":37,"minecraft:dirt":3,"regions_unexplored:medium_grass":9,"minecraft:stone":57,"regions_unexplored:silt_grass_block":7,"regions_unexplored:maple_shrub":1,"minecraft:player_head":1},"minecraft:used":{"minecraft:cooked_mutton":4,"minecraft:stone_sword":41,"minecraft:birch_planks":144,"minecraft:stone_pickaxe":75,"minecraft:stone_shovel":9,"minecraft:chest":2,"minecraft:wooden_pickaxe":6,"minecraft:player_head":1,"minecraft:rotten_flesh":2,"regions_unexplored:tsubaki":1,"regions_unexplored:maple_planks":28,"minecraft:torch":1,"minecraft:dirt":2,"minecraft:crafting_table":5,"minecraft:birch_sign":3,"minecraft:wooden_axe":24,"minecraft:light_weighted_pressure_plate":2,"minecraft:fire_charge":1,"minecraft:wooden_sword":3,"minecraft:stone_axe":83,"minecraft:light_gray_wool":1,"minecraft:cobblestone":23,"minecraft:cooked_porkchop":4,"minecraft:furnace":2,"minecraft:cooked_beef":5,"regions_unexplored:silt_dirt":11},"minecraft:killed":{"minecraft:wolf":1,"minecraft:pig":4,"minecraft:sheep":3,"minecraft:zombie":2,"minecraft:chicken":2,"minecraft:cow":8},"minecraft:dropped":{"minecraft:moss_carpet":4,"minecraft:wheat_seeds":1,"minecraft:stone_shovel":1,"regions_unexplored:maple_branch":2,"regions_unexplored:aster":1,"regions_unexplored:red_maple_sapling":1,"minecraft:wooden_axe":1,"minecraft:wooden_shovel":1,"minecraft:birch_sign":3,"minecraft:wooden_sword":1,"minecraft:wooden_pickaxe":2},"minecraft:picked_up":{"minecraft:wooden_axe":2,"minecraft:crafting_table":1,"minecraft:feather":3,"minecraft:clock":1,"minecraft:chicken":2,"regions_unexplored:silt_dirt":16,"minecraft:golden_pickaxe":1,"minecraft:leather":7,"minecraft:wooden_pickaxe":3,"regions_unexplored:orange_maple_shrub":1,"minecraft:birch_planks":106,"regions_unexplored:maple_planks":5,"regions_unexplored:red_maple_sapling":1,"minecraft:dirt":2,"minecraft:moss_carpet":7,"minecraft:wooden_sword":2,"regions_unexplored:aster":1,"minecraft:wheat_seeds":2,"minecraft:light_weighted_pressure_plate":3,"minecraft:beef":24,"minecraft:stone_pickaxe":1,"minecraft:player_head":2,"minecraft:iron_nugget":10,"minecraft:wooden_shovel":2,"minecraft:light_gray_wool":1,"minecraft:sugar_cane":3,"minecraft:chest":2,"regions_unexplored:orange_coneflower":10,"minecraft:egg":1,"minecraft:furnace":1,"minecraft:stick":10,"minecraft:pumpkin":10,"minecraft:torch":1,"minecraft:fire_charge":1,"minecraft:porkchop":7,"minecraft:stone_sword":1,"minecraft:rotten_flesh":2,"minecraft:stone_shovel":2,"regions_unexplored:tsubaki":1,"minecraft:stone_axe":1,"minecraft:golden_hoe":1,"regions_unexplored:silver_birch_log":37,"regions_unexplored:maple_log":18,"minecraft:golden_apple":1,"minecraft:mutton":10,"minecraft:coal":42,"minecraft:white_wool":4,"minecraft:cobblestone":74}},"DataVersion":3953}